birdseyelib/__init__.py
birdseyelib/controllerInput.py
birdseyelib/emulation.py
birdseyelib/externalTool.py
birdseyelib/joypad.py
birdseyelib/memory.py
birdseyelib/response.py
birdseyelib/socketClient.py
birds_eye_lib-1.1.0.dist-info/METADATA
birds_eye_lib-1.1.0.dist-info/WHEEL
birds_eye_lib-1.1.0.dist-info/top_level.txt
birds_eye_lib-1.1.0.dist-info/RECORD
