Metadata-Version: 2.1
Name: birds-eye-lib
Version: 1.1.0
Summary: A BizHawk external tool + python library for python scripts to communicate with the BizHawk emulator.
Home-page: https://birds-eye.readthedocs.io/
Author: SkiHatDuckie
Author-email: SkiHatDuckie@gmail.com
License: MIT
Classifier: Intended Audience :: Developers
Classifier: License :: OSI Approved :: MIT License
Classifier: Programming Language :: Python
Classifier: Programming Language :: Python :: 3
Classifier: Programming Language :: Python :: 3.6
Classifier: Programming Language :: Python :: 3.7
Classifier: Programming Language :: Python :: 3.8
Classifier: Programming Language :: Python :: 3.9
Classifier: Programming Language :: Python :: 3.10
Classifier: Programming Language :: Python :: 3.11
Classifier: Programming Language :: Python :: 3.12
Classifier: Operating System :: OS Independent
